pryce/__init__.py
pryce/ero.py
pryce/examples.py
pryce/ls.py
pryce/ls2.py
pryce/models.py
pryce/simple.py
pryce-0.2.dist-info/METADATA
pryce-0.2.dist-info/WHEEL
pryce-0.2.dist-info/top_level.txt
pryce-0.2.dist-info/RECORD
