Metadata-Version: 2.1
Name: pryce
Version: 0.2
Summary: Option pricing
Home-page: https://github.com/soerenwolfers/pryce
Author: Soeren Wolfers
Author-email: soeren.wolfers@gmail.com
License: UNKNOWN
Platform: UNKNOWN
Requires-Python: >=3.6
Requires-Dist: numpy
Requires-Dist: scipy
Requires-Dist: swutil
Requires-Dist: smolyak
